[
    {
        "key": "dbln",
        "value": "%7B%2261562688607607%22%3A%22Ykz7gFpU%22%7D",
        "domain": "facebook.com",
        "path": "/login/device-based/",
        "hostOnly": false,
        "creation": "2025-07-25T15:12:53.335Z",
        "lastAccessed": "2025-07-25T15:12:53.336Z"
    },
    {
        "key": "sb",
        "value": "Es74Z-7KJfN90OX7GoNu2-zO",
        "domain": "facebook.com",
        "path": "/",
        "hostOnly": false,
        "creation": "2025-07-25T15:12:53.336Z",
        "lastAccessed": "2025-07-25T15:12:53.336Z"
    },
    {
        "key": "ps_l",
        "value": "1",
        "domain": "facebook.com",
        "path": "/",
        "hostOnly": false,
        "creation": "2025-07-25T15:12:53.336Z",
        "lastAccessed": "2025-07-25T15:12:53.336Z"
    },
    {
        "key": "ps_n",
        "value": "1",
        "domain": "facebook.com",
        "path": "/",
        "hostOnly": false,
        "creation": "2025-07-25T15:12:53.336Z",
        "lastAccessed": "2025-07-25T15:12:53.336Z"
    },
    {
        "key": "wd",
        "value": "1400x961",
        "domain": "facebook.com",
        "path": "/",
        "hostOnly": false,
        "creation": "2025-07-25T15:12:53.336Z",
        "lastAccessed": "2025-07-25T15:12:53.336Z"
    },
    {
        "key": "locale",
        "value": "en_GB",
        "domain": "facebook.com",
        "path": "/",
        "hostOnly": false,
        "creation": "2025-07-25T15:12:53.336Z",
        "lastAccessed": "2025-07-25T15:12:53.336Z"
    },
    {
        "key": "c_user",
        "value": "61562688607607",
        "domain": "facebook.com",
        "path": "/",
        "hostOnly": false,
        "creation": "2025-07-25T15:12:53.336Z",
        "lastAccessed": "2025-07-25T15:12:53.336Z"
    },
    {
        "key": "datr",
        "value": "7omDaE6adTWvsYBEMp5vwET4",
        "domain": "facebook.com",
        "path": "/",
        "hostOnly": false,
        "creation": "2025-07-25T15:12:53.336Z",
        "lastAccessed": "2025-07-25T15:12:53.336Z"
    },
    {
        "key": "presence",
        "value": "C%7B%22lm3%22%3A%22sc.24414374424823850%22%2C%22t3%22%3A%5B%7B%22o%22%3A0%2C%22i%22%3A%22sc.8260646640726085%22%7D%2C%7B%22o%22%3A0%2C%22i%22%3A%22g.5960889074027890%22%7D%2C%7B%22o%22%3A0%2C%22i%22%3A%22g.24507104978907108%22%7D%5D%2C%22utc3%22%3A1753454091436%2C%22v%22%3A1%7D",
        "domain": "facebook.com",
        "path": "/",
        "hostOnly": false,
        "creation": "2025-07-25T15:12:53.336Z",
        "lastAccessed": "2025-07-25T15:12:53.336Z"
    },
    {
        "key": "fr",
        "value": "1lWOpPxk3oIfEhbar.AWddMwSwQtVpdE_RB__Kig8h5jzclX2aoHE2Gc868ASIZpN7zvQ.Bog5sW..AAA.0.0.Bog5sW.AWd_ql1OIbfpmON80F-6RzmeBvE",
        "domain": "facebook.com",
        "path": "/",
        "hostOnly": false,
        "creation": "2025-07-25T15:12:53.336Z",
        "lastAccessed": "2025-07-25T15:12:53.336Z"
    },
    {
        "key": "xs",
        "value": "48%3ApGTMQ6y03xthOA%3A2%3A1753450991%3A-1%3A-1%3A%3AAcXeHU_HwGVZ_-fJ3aflEJAQjqAYuUGux7xQBfo34w",
        "domain": "facebook.com",
        "path": "/",
        "hostOnly": false,
        "creation": "2025-07-25T15:12:53.336Z",
        "lastAccessed": "2025-07-25T15:12:53.336Z"
    }
]
